django_iplant_auth-0.1.21.dist-info/DESCRIPTION.rst
django_iplant_auth-0.1.21.dist-info/METADATA
django_iplant_auth-0.1.21.dist-info/RECORD
django_iplant_auth-0.1.21.dist-info/WHEEL
django_iplant_auth-0.1.21.dist-info/metadata.json
django_iplant_auth-0.1.21.dist-info/top_level.txt
iplantauth/__init__.py
iplantauth/admin.py
iplantauth/authBackends.py
iplantauth/decorators.py
iplantauth/exceptions.py
iplantauth/models.py
iplantauth/session.py
iplantauth/settings.py
iplantauth/token.py
iplantauth/urls.py
iplantauth/views.py
iplantauth/migrations/0001_initial.py
iplantauth/migrations/0002_resize_charfield_mysql_limits.py
iplantauth/migrations/__init__.py
iplantauth/protocol/__init__.py
iplantauth/protocol/cas.py
iplantauth/protocol/globus.py
iplantauth/protocol/jwt_oauth.py
iplantauth/protocol/ldap.py
iplantauth/protocol/oauth.py
iplantauth/protocol/wso2.py
