Metadata-Version: 2.0
Name: django-iplant-auth
Version: 0.1.21
Summary: Authentication support for iPlantCollaborative.
Home-page: https://github.com/iPlantCollaborativeOpenSource/django-iplant-auth
Author: iPlantCollaborative
Author-email: atmodevs@gmail.com
License: BSD License, 3 clause
Platform: UNKNOWN
Classifier: Development Status :: 3 - Alpha
Classifier: Environment :: Web Environment
Classifier: Framework :: Django
Classifier: Framework :: Django :: 1.7
Classifier: Framework :: Django :: 1.8
Classifier: Intended Audience :: Developers
Classifier: Intended Audience :: Information Technology
Classifier: License :: OSI Approved :: BSD License
Classifier: Natural Language :: English
Classifier: Operating System :: OS Independent
Classifier: Programming Language :: Python
Classifier: Topic :: Software Development :: Libraries
Classifier: Topic :: System :: Systems Administration
Requires-Dist: caslib.py (==2.2.2)
Requires-Dist: oauth2client (==1.5.1)
Requires-Dist: djangorestframework (==3.3.3)
Requires-Dist: jwt.py (==0.1.0)
Requires-Dist: python-ldap (==2.4.19)
Requires-Dist: requests (==2.7.0)
Requires-Dist: threepio (==0.2)
